pairpot/AUCell.py
pairpot/__init__.py
pairpot/core.py
pairpot/db.py
pairpot/download.py
pairpot/label_propagation.cpython-310-x86_64-linux-gnu.so
pairpot/lassoview.py
pairpot/normalize.py
pairpot/pairPotProc.py
pairpot/pairview.py
pairpot/resources/Cell_marker_Seq.xlsx
pairpot/resources/PanglaoDB_markers_27_Mar_2020.tsv
pairpot_library/AUCell.py
pairpot_library/__init__.py
pairpot_library/core.py
pairpot_library/db.py
pairpot_library/lassoview.py
pairpot_library/normalize.py
pairpot_library/pairPotProc.py
pairpot_library/pairview.py
pairpot_library/test.py
pairpot-0.0.3.dist-info/LICENSE
pairpot-0.0.3.dist-info/METADATA
pairpot-0.0.3.dist-info/WHEEL
pairpot-0.0.3.dist-info/top_level.txt
pairpot-0.0.3.dist-info/RECORD
