Metadata-Version: 2.1
Name: pairpot
Version: 0.0.3
Summary: Pairpot: a database with real-time lasso-based analysis tailored for paired single-cell and spatial transcriptomics.
Home-page: https://github.com/lyotvincent/Pairpot
Author: Zhihan Ruan, Zhenjie Zhang, and Jian Liu.
Author-email: rrrzhan@mail.nankai.edu.cn
License: UNKNOWN
Platform: UNKNOWN
Classifier: Programming Language :: Python :: 3
Classifier: License :: OSI Approved :: MIT License
Classifier: Operating System :: OS Independent
Requires-Python: >=3.6
License-File: LICENSE
Requires-Dist: h5py
Requires-Dist: numpy
Requires-Dist: pandas
Requires-Dist: anndata
Requires-Dist: scanpy
Requires-Dist: pkg-resources
Requires-Dist: scipy
